CHANGELOG.txt
LICENSE.txt
MANIFEST.in
README.md
setup.py
create_figs/changing_doses.py
create_figs/paper.py
create_figs/single.py
hrhr.egg-info/PKG-INFO
hrhr.egg-info/SOURCES.txt
hrhr.egg-info/dependency_links.txt
hrhr.egg-info/not-zip-safe
hrhr.egg-info/top_level.txt
model/config.py
model/config_classes.py
model/ode_system.py
model/outputs.py
model/params.py
model/simulator.py
model/strategy_arrays.py
model/utils.py
param_scan/fns/calc_full_scan.py
param_scan/fns/calc_method_IVT.py
param_scan/fns/calc_method_contour.py
param_scan/fns/calc_other_strats.py
param_scan/fns/calc_sing_ps_run.py
param_scan/fns/config.py
param_scan/fns/pars.py
param_scan/fns/post_process.py
param_scan/run/r1_run.py
param_scan/run/r2_combine_outputs.py
param_scan/run/r3_analyse.py
plotting/consts.py
plotting/figures.py
plotting/traces.py
plotting/utils.py