Metadata-Version: 2.1
Name: hrhr
Version: 0.0.3
Summary: HRHR model
Home-page: https://github.com/nt409/HRHR
Author: Nick Taylor
Author-email: nt409@cam.ac.uk
License: MIT
Platform: UNKNOWN
